munch_mailsend/__about__.py
munch_mailsend/__init__.py
munch_mailsend/admin.py
munch_mailsend/amqp.py
munch_mailsend/apps.py
munch_mailsend/backend.py
munch_mailsend/celery.py
munch_mailsend/managers.py
munch_mailsend/models.py
munch_mailsend/relay.py
munch_mailsend/settings.py
munch_mailsend/signals.py
munch_mailsend/tasks.py
munch_mailsend/management/__init__.py
munch_mailsend/management/commands/__init__.py
munch_mailsend/management/commands/cache_mailstatus.py
munch_mailsend/management/commands/clear_mailstatus.py
munch_mailsend/management/commands/disable_worker.py
munch_mailsend/management/commands/enable_worker.py
munch_mailsend/management/commands/list_messages.py
munch_mailsend/management/commands/list_queues.py
munch_mailsend/management/commands/list_workers.py
munch_mailsend/management/commands/sign_dkim.py
munch_mailsend/management/commands/verify_dkim.py
munch_mailsend/migrations/0001_initial.py
munch_mailsend/migrations/__init__.py
munch_mailsend/policies/__init__.py
munch_mailsend/policies/mx/__init__.py
munch_mailsend/policies/mx/greylist.py
munch_mailsend/policies/mx/pool.py
munch_mailsend/policies/mx/rate_limit.py
munch_mailsend/policies/mx/warm_up.py
munch_mailsend/policies/relay/__init__.py
munch_mailsend/policies/relay/dkim.py
munch_mailsend/policies/relay/headers.py
munch_mailsend/utils/__init__.py
munch_mailsend/utils/backoff.py
munch_mailsend/utils/tasks.py
munch_mailsend/utils/dkim/__init__.py
munch_mailsend/utils/dkim/asn1.py
munch_mailsend/utils/dkim/canonicalization.py
munch_mailsend/utils/dkim/crypto.py
munch_mailsend/utils/dkim/dnsplug.py
munch_mailsend/utils/dkim/exceptions.py
munch_mailsend/utils/dkim/utils.py
munch_mailsend-0.1.1.dist-info/DESCRIPTION.rst
munch_mailsend-0.1.1.dist-info/METADATA
munch_mailsend-0.1.1.dist-info/RECORD
munch_mailsend-0.1.1.dist-info/WHEEL
munch_mailsend-0.1.1.dist-info/metadata.json
munch_mailsend-0.1.1.dist-info/top_level.txt
munch_mailsend_tests/__init__.py
munch_mailsend_tests/models.py
munch_mailsend_tests/settings.py
munch_mailsend_tests/urls.py
munch_mailsend_tests/migrations/0001_initial.py
munch_mailsend_tests/migrations/__init__.py
munch_mailsend_tests/tests/__init__.py
