Metadata-Version: 2.0
Name: munch-mailsend
Version: 0.1.1
Summary: Sending mass emails with Munch.
Home-page: https://github.com/crunchmail/munch-mailsend
Author: Crunchmail
Author-email: dev@crunchmail.com
License: 0.1.1
Platform: UNKNOWN
Classifier: Environment :: Web Environment
Classifier: Framework :: Django
Classifier: Framework :: Django :: 1.9
Classifier: Intended Audience :: Developers
Classifier: Operating System :: OS Independent
Classifier: Programming Language :: Python
Classifier: Programming Language :: Python :: 3
Classifier: Programming Language :: Python :: 3.4
Classifier: Topic :: Internet :: WWW/HTTP
Classifier: Topic :: Internet :: WWW/HTTP :: Dynamic Content
Classifier: License :: OSI Approved :: GNU Affero General Public License v3 or later (AGPLv3+)
Provides-Extra: tests
Requires-Dist: flake8 (==2.5.4); extra == 'tests'
Requires-Dist: bumpversion (==0.5.3); extra == 'tests'
Requires-Dist: libfaketime (==0.2.1); extra == 'tests'
